README.md
asyncblink.py
pyproject.toml
asyncblink.egg-info/PKG-INFO
asyncblink.egg-info/SOURCES.txt
asyncblink.egg-info/dependency_links.txt
asyncblink.egg-info/requires.txt
asyncblink.egg-info/top_level.txt