Metadata-Version: 2.1
Name: asyncblink
Version: 0.4.0
Summary: Signals with coroutines!
Author: Juca Crispim
Project-URL: Homepage, https://pypi.python.org/pypi/asyncblink
Classifier: Programming Language :: Python :: 3
Classifier: License :: OSI Approved :: GNU General Public License (GPL)
Classifier: Operating System :: OS Independent
Classifier: Topic :: Software Development :: Libraries :: Python Modules
Requires-Python: >=3.9
